vllm_dolphin/__init__.py
vllm_dolphin/dolphin.py
vllm_dolphin/donut_swin.py
vllm_dolphin-0.1.dist-info/licenses/LICENSE
vllm_dolphin-0.1.dist-info/METADATA
vllm_dolphin-0.1.dist-info/WHEEL
vllm_dolphin-0.1.dist-info/entry_points.txt
vllm_dolphin-0.1.dist-info/top_level.txt
vllm_dolphin-0.1.dist-info/RECORD
