Metadata-Version: 2.4
Name: vllm_dolphin
Version: 0.1
License-File: LICENSE
Requires-Dist: vllm>=0.9.0
Requires-Dist: vllm-mbart>=0.1
Dynamic: license-file
Dynamic: requires-dist
